_SERD.cpython-310-darwin.so
SERD/SERD.py
SERD/__init__.py
SERD-0.1.2.dist-info/LICENSE
SERD-0.1.2.dist-info/METADATA
SERD-0.1.2.dist-info/WHEEL
SERD-0.1.2.dist-info/top_level.txt
SERD-0.1.2.dist-info/RECORD
