Metadata-Version: 2.1
Name: SERD
Version: 0.1.2
Summary: A Python package to detect solvent-exposed residues of a target biomolecule.
Home-page: https://github.com/jvsguerra/SERD
Author: João Victor da Silva Guerra, Gabriel Ernesto Jara, José Geraldo de Carvalho Pereira
Author-email: jvsguerra@gmail.com
License: UNKNOWN
Project-URL: Source, https://github.com/jvsguerra/SERD/
Project-URL: Issues, https://github.com/jvsguerra/SERD/issues
Keywords: structural biology,proteins,biomolecular surface,solvent-exposed residues
Platform: UNKNOWN
Classifier: Development Status :: 4 - Beta
Classifier: Intended Audience :: Science/Research
Classifier: Topic :: Scientific/Engineering :: Bio-Informatics
Classifier: Topic :: Scientific/Engineering :: Chemistry
Classifier: License :: OSI Approved :: GNU General Public License v3 (GPLv3)
Classifier: Programming Language :: Python :: 3
Classifier: Programming Language :: Python :: 3.8
Classifier: Programming Language :: Python :: 3.9
Classifier: Programming Language :: Python :: 3.10
Classifier: Programming Language :: Python :: 3 :: Only
Requires-Python: >=3.8, <4
Requires-Dist: networkx (>=2.8.6)
Requires-Dist: numpy (>=1.23.2)
Requires-Dist: pyKVFinder (>=0.4.2)
Requires-Dist: scipy (>=1.9.0)
